llm/__init__.py
llm/__main__.py
llm/cli.py
llm/embeddings.py
llm/embeddings_migrations.py
llm/errors.py
llm/hookspecs.py
llm/migrations.py
llm/models.py
llm/plugins.py
llm/templates.py
llm/utils.py
llm/default_plugins/__init__.py
llm/default_plugins/openai_models.py
visi/__init__.py
visi/cli.py
visi/hubapi.py
visi/luggage.py
visi-4.1.1.dist-info/LICENSE
visi-4.1.1.dist-info/METADATA
visi-4.1.1.dist-info/WHEEL
visi-4.1.1.dist-info/entry_points.txt
visi-4.1.1.dist-info/top_level.txt
visi-4.1.1.dist-info/RECORD
