Metadata-Version: 2.1
Name: visi
Version: 4.1.1
Summary: A CLI utility for Visi
Home-page: https://github.com/fikisipi/gpr
Author: Filip Dimitrovski
License: Filip Dimitrovski
Requires-Python: >=3.9
License-File: LICENSE
Requires-Dist: click
Requires-Dist: openai>=1.0
Requires-Dist: term-image==0.7.1
Requires-Dist: uvicorn
Requires-Dist: click-default-group>=1.2.3
Requires-Dist: pydantic>=1.10.2
Requires-Dist: PyYAML
Requires-Dist: pluggy
Requires-Dist: python-ulid
Requires-Dist: google-cloud-storage
Requires-Dist: google-generativeai
Requires-Dist: setuptools
Requires-Dist: pip
Requires-Dist: pyreadline3; sys_platform == "win32"
Requires-Dist: puremagic
Provides-Extra: test
Requires-Dist: pytest; extra == "test"
Requires-Dist: numpy; extra == "test"
Requires-Dist: pytest-httpx>=0.33.0; extra == "test"
Requires-Dist: pytest-asyncio; extra == "test"
Requires-Dist: cogapp; extra == "test"
Requires-Dist: mypy>=1.10.0; extra == "test"
Requires-Dist: black>=24.1.0; extra == "test"
Requires-Dist: ruff; extra == "test"
Requires-Dist: types-click; extra == "test"
Requires-Dist: types-PyYAML; extra == "test"
Requires-Dist: types-setuptools; extra == "test"
